pyls_jsonrpc/__init__.py
pyls_jsonrpc/_version.py
pyls_jsonrpc/dispatchers.py
pyls_jsonrpc/endpoint.py
pyls_jsonrpc/exceptions.py
pyls_jsonrpc/streams.py
python_jsonrpc_server-0.3.4.dist-info/LICENSE
python_jsonrpc_server-0.3.4.dist-info/METADATA
python_jsonrpc_server-0.3.4.dist-info/WHEEL
python_jsonrpc_server-0.3.4.dist-info/top_level.txt
python_jsonrpc_server-0.3.4.dist-info/RECORD
