Metadata-Version: 2.1
Name: python-jsonrpc-server
Version: 0.3.4
Summary: JSON RPC 2.0 server library
Home-page: https://github.com/palantir/python-jsonrpc-server
Author: Palantir Technologies, Inc.
License: UNKNOWN
Platform: UNKNOWN
Provides-Extra: test
